custom_numbers/__init__.py
custom_numbers/custom_numbers.py
custom_numbers/py.typed
custom_numbers-1.3.1.dist-info/METADATA
custom_numbers-1.3.1.dist-info/WHEEL
custom_numbers-1.3.1.dist-info/licenses/LICENSE
custom_numbers-1.3.1.dist-info/RECORD
