Metadata-Version: 2.3
Name: custom_numbers
Version: 1.3.1
Summary: Swiss-army knife for numbers of custom numeral systems.
Project-URL: Homepage, https://github.com/StrayFeral/custom_numbers
Project-URL: Bug Tracker, https://github.com/StrayFeral/custom_numbers/issues
Author-email: Evgueni Antonov <Evgueni.Antonov@gmail.com>
License: MIT License
License-File: LICENSE
Keywords: counter,math,mathematics,number,numbers,numeral
Classifier: Development Status :: 5 - Production/Stable
Classifier: License :: OSI Approved :: MIT License
Classifier: Operating System :: OS Independent
Classifier: Programming Language :: Python :: 3
Classifier: Topic :: Scientific/Engineering :: Mathematics
Requires-Python: >=3.8
